has_status/__init__.py
has_status/asgi.py
has_status/settings.py
has_status/urls.py
has_status/wsgi.py
model_status/__init__.py
model_status/apps.py
model_status/models.py
model_status/serializers.py
model_status/urls.py
model_status/views.py
model_status/locale/ar/LC_MESSAGES/django.mo
model_status/locale/ar/LC_MESSAGES/django.po
model_status/migrations/0001_initial.py
model_status/migrations/__init__.py
model_status/templates/model_status/_model_status_log.html
model_status-1.1.0.dist-info/LICENSE
model_status-1.1.0.dist-info/METADATA
model_status-1.1.0.dist-info/WHEEL
model_status-1.1.0.dist-info/top_level.txt
model_status-1.1.0.dist-info/RECORD
